{
    "Mangrove": {
        "f1-score": {
            "90th": [
                0.9691544582180788,
                0.9959183673469388
            ],
            "95th": [
                0.9655172413793104,
                0.9961685823754789
            ],
            "99th": [
                0.9599983870967743,
                1.0
            ],
            "mean": 0.9837774392684296,
            "median": 0.9841269841269841
        },
        "precision": {
            "90th": [
                0.9401548743654007,
                0.991869918699187
            ],
            "95th": [
                0.9333333333333333,
                0.9923664122137404
            ],
            "99th": [
                0.9230739415623137,
                1.0
            ],
            "mean": 0.9681970727677551,
            "median": 0.96875
        },
        "producer_accuracy": {
            "90th": [
                94.01548743654006,
                99.1869918699187
            ],
            "95th": [
                93.33333333333333,
                99.23664122137404
            ],
            "99th": [
                92.30739415623137,
                100.0
            ],
            "mean": 96.8197072767755,
            "median": 96.875
        },
        "recall": {
            "90th": [
                1.0,
                1.0
            ],
            "95th": [
                1.0,
                1.0
            ],
            "99th": [
                1.0,
                1.0
            ],
            "mean": 1.0,
            "median": 1.0
        },
        "support": {
            "90th": [
                108.0,
                133.0
            ],
            "95th": [
                105.975,
                135.02499999999986
            ],
            "99th": [
                101.0,
                141.0
            ],
            "mean": 120.878,
            "median": 121.0
        },
        "user_accuracy": {
            "90th": [
                100.0,
                100.0
            ],
            "95th": [
                100.0,
                100.0
            ],
            "99th": [
                100.0,
                100.0
            ],
            "mean": 100.0,
            "median": 100.0
        }
    },
    "Other": {
        "f1-score": {
            "90th": [
                0.9699134199134198,
                0.9961104517524751
            ],
            "95th": [
                0.966542750929368,
                0.996309963099631
            ],
            "99th": [
                0.9609375000000001,
                1.0
            ],
            "mean": 0.9842959917927742,
            "median": 0.9847328244274809
        },
        "precision": {
            "90th": [
                1.0,
                1.0
            ],
            "95th": [
                1.0,
                1.0
            ],
            "99th": [
                1.0,
                1.0
            ],
            "mean": 1.0,
            "median": 1.0
        },
        "producer_accuracy": {
            "90th": [
                100.0,
                100.0
            ],
            "95th": [
                100.0,
                100.0
            ],
            "99th": [
                100.0,
                100.0
            ],
            "mean": 100.0,
            "median": 100.0
        },
        "recall": {
            "90th": [
                0.9415843709746672,
                0.9922510435301133
            ],
            "95th": [
                0.935251798561151,
                0.9926470588235294
            ],
            "99th": [
                0.924812030075188,
                1.0
            ],
            "mean": 0.9691955650504074,
            "median": 0.9699248120300752
        },
        "support": {
            "90th": [
                117.0,
                142.0
            ],
            "95th": [
                114.975,
                144.02499999999986
            ],
            "99th": [
                109.0,
                149.0
            ],
            "mean": 129.122,
            "median": 129.0
        },
        "user_accuracy": {
            "90th": [
                94.15843709746672,
                99.22510435301133
            ],
            "95th": [
                93.5251798561151,
                99.26470588235294
            ],
            "99th": [
                92.4812030075188,
                100.0
            ],
            "mean": 96.91955650504073,
            "median": 96.99248120300751
        }
    },
    "accuracy": {
        "90th": [
            0.968,
            0.996
        ],
        "95th": [
            0.968,
            0.996
        ],
        "99th": [
            0.96,
            1.0
        ],
        "mean": 0.9841020000000001,
        "median": 0.984
    },
    "cohen_kappa": {
        "90th": [
            0.9360613810741688,
            0.9919897468760013
        ],
        "95th": [
            0.9355646195904894,
            0.9919989758689112
        ],
        "99th": [
            0.9200818361997315,
            1.0
        ],
        "mean": 0.9680879619594525,
        "median": 0.9679754051111253
    },
    "macro avg": {
        "f1-score": {
            "90th": [
                0.9679979518689197,
                0.9959948092728176
            ],
            "95th": [
                0.9677490601682318,
                0.995999423917044
            ],
            "99th": [
                0.9599769467213115,
                1.0
            ],
            "mean": 0.9840367155306019,
            "median": 0.9839835992055865
        },
        "precision": {
            "90th": [
                0.9700774371827003,
                0.9959349593495934
            ],
            "95th": [
                0.9666666666666667,
                0.9961832061068703
            ],
            "99th": [
                0.9615369707811569,
                1.0
            ],
            "mean": 0.9840985363838777,
            "median": 0.984375
        },
        "recall": {
            "90th": [
                0.9707921854873337,
                0.9961255217650566
            ],
            "95th": [
                0.9676258992805755,
                0.9963235294117647
            ],
            "99th": [
                0.9624060150375939,
                1.0
            ],
            "mean": 0.9845977825252037,
            "median": 0.9849624060150376
        }
    },
    "weighted avg": {
        "f1-score": {
            "90th": [
                0.9680824476650564,
                0.9960004547713054
            ],
            "95th": [
                0.9679175523349436,
                0.9960013535506534
            ],
            "99th": [
                0.9601027564590232,
                1.0
            ],
            "mean": 0.984106930253922,
            "median": 0.9840123163769324
        },
        "precision": {
            "90th": [
                0.9701512605042016,
                0.9960328004335457
            ],
            "95th": [
                0.969841726618705,
                0.9960347826086956
            ],
            "99th": [
                0.9632785552445688,
                1.0
            ],
            "mean": 0.9847293078515588,
            "median": 0.9845289256198347
        },
        "recall": {
            "90th": [
                0.968,
                0.996
            ],
            "95th": [
                0.968,
                0.996
            ],
            "99th": [
                0.96,
                1.0
            ],
            "mean": 0.9841020000000001,
            "median": 0.984
        }
    }
}