{
    "Mangrove": {
        "f1-score": 0.9717741935483872,
        "precision": 0.9620758483033932,
        "recall": 0.9816700610997964,
        "support": 491
    },
    "Other": {
        "f1-score": 0.9722222222222221,
        "precision": 0.9819639278557114,
        "recall": 0.962671905697446,
        "support": 509
    },
    "accuracy": 0.972,
    "accuracy_conf_interval": [
        0.008555708830950248,
        0.010225115432111274,
        0.012155366814703708,
        0.013459590721860759
    ],
    "cls_confidence_intervals": {
        "Mangrove": [
            0.013995472938675488,
            0.01672629692670973,
            0.019883812162874322,
            0.022017268403526073
        ],
        "Other": [
            0.009770399555805128,
            0.01167681898132808,
            0.013881116442088995,
            0.0153705066182788
        ]
    },
    "cohen_kappa": 0.9440020159274266,
    "confusion_matrix": [
        [
            482,
            9
        ],
        [
            19,
            490
        ]
    ],
    "macro avg": {
        "f1-score": 0.9719982078853047,
        "precision": 0.9720198880795523,
        "recall": 0.9721709833986212,
        "support": 1000
    },
    "producer_accuracy": [
        96.20758483033931,
        98.19639278557113
    ],
    "user_accuracy": [
        98.16700610997964,
        96.2671905697446
    ],
    "weighted avg": {
        "f1-score": 0.9720022401433691,
        "precision": 0.9721988807955232,
        "recall": 0.972,
        "support": 1000
    }
}