{
    "Mangrove": {
        "f1-score": {
            "90th": [
                0.8273632561132561,
                0.8909180918091809
            ],
            "95th": [
                0.8208092485549133,
                0.8961573506644303
            ],
            "99th": [
                0.8083785844460148,
                0.9054446832219039
            ],
            "mean": 0.8595710724661867,
            "median": 0.8596501732027542
        },
        "precision": {
            "90th": [
                0.9700531268290487,
                1.0
            ],
            "95th": [
                0.9664429530201343,
                1.0
            ],
            "99th": [
                0.9592989174017643,
                1.0
            ],
            "mean": 0.987118046418912,
            "median": 0.9874213836477987
        },
        "producer_accuracy": {
            "90th": [
                97.00531268290487,
                100.0
            ],
            "95th": [
                96.64429530201343,
                100.0
            ],
            "99th": [
                95.92989174017643,
                100.0
            ],
            "mean": 98.71180464189119,
            "median": 98.74213836477988
        },
        "recall": {
            "90th": [
                0.7122641509433962,
                0.8113207547169812
            ],
            "95th": [
                0.7029702970297029,
                0.8190968138565166
            ],
            "99th": [
                0.6857142857142857,
                0.8351689051689051
            ],
            "mean": 0.7617450600969231,
            "median": 0.7614678899082569
        },
        "support": {
            "90th": [
                185.0,
                218.0
            ],
            "95th": [
                182.0,
                220.02499999999986
            ],
            "99th": [
                174.995,
                225.00499999999988
            ],
            "mean": 200.958,
            "median": 201.0
        },
        "user_accuracy": {
            "90th": [
                71.22641509433963,
                81.13207547169812
            ],
            "95th": [
                70.29702970297029,
                81.90968138565165
            ],
            "99th": [
                68.57142857142857,
                83.51689051689051
            ],
            "mean": 76.17450600969231,
            "median": 76.14678899082568
        }
    },
    "Other": {
        "f1-score": {
            "90th": [
                0.8618266978922717,
                0.9125885433808902
            ],
            "95th": [
                0.8571428571428572,
                0.9172022985322625
            ],
            "99th": [
                0.8459619855463375,
                0.9244062395008398
            ],
            "mean": 0.8874706102263238,
            "median": 0.8878504672897196
        },
        "precision": {
            "90th": [
                0.7628358530320973,
                0.8464912280701754
            ],
            "95th": [
                0.7562999166608793,
                0.8535564853556485
            ],
            "99th": [
                0.7391222826086956,
                0.8663981106612685
            ],
            "mean": 0.8045525792847563,
            "median": 0.8047808764940239
        },
        "producer_accuracy": {
            "90th": [
                76.28358530320973,
                84.64912280701753
            ],
            "95th": [
                75.62999166608792,
                85.35564853556485
            ],
            "99th": [
                73.91222826086955,
                86.63981106612685
            ],
            "mean": 80.45525792847563,
            "median": 80.47808764940238
        },
        "recall": {
            "90th": [
                0.9767387524451205,
                1.0
            ],
            "95th": [
                0.9743556701030928,
                1.0
            ],
            "99th": [
                0.9692299762093577,
                1.0
            ],
            "mean": 0.9899927784286572,
            "median": 0.9901477832512315
        },
        "support": {
            "90th": [
                182.0,
                215.0
            ],
            "95th": [
                179.975,
                218.0
            ],
            "99th": [
                174.995,
                225.00499999999988
            ],
            "mean": 199.042,
            "median": 199.0
        },
        "user_accuracy": {
            "90th": [
                97.67387524451205,
                100.0
            ],
            "95th": [
                97.43556701030927,
                100.0
            ],
            "99th": [
                96.92299762093576,
                100.0
            ],
            "mean": 98.99927784286571,
            "median": 99.01477832512316
        }
    },
    "accuracy": {
        "90th": [
            0.85,
            0.9025
        ],
        "95th": [
            0.8425,
            0.9075
        ],
        "99th": [
            0.835,
            0.915
        ],
        "mean": 0.875325,
        "median": 0.875
    },
    "cohen_kappa": {
        "90th": [
            0.7,
            0.8020525487212534
        ],
        "95th": [
            0.6897421415145263,
            0.8109078140816488
        ],
        "99th": [
            0.6727710720211465,
            0.8293874977161371
        ],
        "mean": 0.7505489174392962,
        "median": 0.7504659622387089
    },
    "macro avg": {
        "f1-score": {
            "90th": [
                0.8470785101435833,
                0.9001785268654139
            ],
            "95th": [
                0.8414322250639386,
                0.9047676364720176
            ],
            "99th": [
                0.8325879537409827,
                0.9141426140989863
            ],
            "mean": 0.8735208413462551,
            "median": 0.8734689745925701
        },
        "precision": {
            "90th": [
                0.8747618260657375,
                0.9174331511439543
            ],
            "95th": [
                0.8710114815532777,
                0.9215983224603913
            ],
            "99th": [
                0.8618840096532648,
                0.9274410156680689
            ],
            "mean": 0.8958353128518343,
            "median": 0.8958349871662565
        },
        "recall": {
            "90th": [
                0.8510902521633825,
                0.9005108112663451
            ],
            "95th": [
                0.8468865735415899,
                0.9056964573268921
            ],
            "99th": [
                0.8373405321054613,
                0.9133655620142794
            ],
            "mean": 0.8758689192627901,
            "median": 0.8759372100604328
        }
    },
    "weighted avg": {
        "f1-score": {
            "90th": [
                0.8470088424885023,
                0.9010207471817898
            ],
            "95th": [
                0.8413330205056679,
                0.9061187392960155
            ],
            "99th": [
                0.8320192930721967,
                0.914313836563871
            ],
            "mean": 0.8737007452569755,
            "median": 0.8735550010243966
        },
        "precision": {
            "90th": [
                0.8787965476679584,
                0.915121447395618
            ],
            "95th": [
                0.8755503468577975,
                0.9188844507638231
            ],
            "99th": [
                0.8682935376275995,
                0.9256989304997055
            ],
            "mean": 0.8966854499210867,
            "median": 0.8965678414371059
        },
        "recall": {
            "90th": [
                0.85,
                0.9025
            ],
            "95th": [
                0.8425,
                0.9075
            ],
            "99th": [
                0.835,
                0.915
            ],
            "mean": 0.875325,
            "median": 0.875
        }
    }
}