{
    "Mangrove": {
        "f1-score": {
            "90th": [
                0.9546783131338588,
                0.9743589743589745
            ],
            "95th": [
                0.9523784825133372,
                0.9762387977928227
            ],
            "99th": [
                0.9485562546673657,
                0.9789802265173185
            ],
            "mean": 0.9647518818940995,
            "median": 0.9649289099526066
        },
        "precision": {
            "90th": [
                0.942684507224778,
                0.9721697592224431
            ],
            "95th": [
                0.9395785984848485,
                0.974844083050446
            ],
            "99th": [
                0.9322650735640117,
                0.9781746031746031
            ],
            "mean": 0.9578807881147254,
            "median": 0.9581271169555688
        },
        "producer_accuracy": {
            "90th": [
                94.26845072247781,
                97.21697592224432
            ],
            "95th": [
                93.95785984848484,
                97.48440830504461
            ],
            "99th": [
                93.22650735640116,
                97.81746031746032
            ],
            "mean": 95.78807881147254,
            "median": 95.81271169555689
        },
        "recall": {
            "90th": [
                0.9587628865979382,
                0.9836751319672472
            ],
            "95th": [
                0.9563490000990001,
                0.9856270197259904
            ],
            "99th": [
                0.9504753005774874,
                0.989496018072501
            ],
            "mean": 0.9717924266633505,
            "median": 0.9721669980119284
        },
        "support": {
            "90th": [
                469.0,
                521.0
            ],
            "95th": [
                463.0,
                526.0
            ],
            "99th": [
                451.995,
                534.0049999999999
            ],
            "mean": 494.3545,
            "median": 494.0
        },
        "user_accuracy": {
            "90th": [
                95.87628865979381,
                98.36751319672472
            ],
            "95th": [
                95.63490000990001,
                98.56270197259904
            ],
            "99th": [
                95.04753005774874,
                98.9496018072501
            ],
            "mean": 97.17924266633504,
            "median": 97.21669980119285
        }
    },
    "Other": {
        "f1-score": {
            "90th": [
                0.9547844374342797,
                0.9748559042796184
            ],
            "95th": [
                0.9530452306314374,
                0.9760968056204605
            ],
            "99th": [
                0.9487688031460823,
                0.9790361911066976
            ],
            "mean": 0.9650414484113934,
            "median": 0.9650768905615891
        },
        "precision": {
            "90th": [
                0.9590147925204917,
                0.9838073038073037
            ],
            "95th": [
                0.9568961091836012,
                0.9858299595141701
            ],
            "99th": [
                0.9511698035037879,
                0.9898585213063206
            ],
            "mean": 0.9720248688334691,
            "median": 0.9722772277227723
        },
        "producer_accuracy": {
            "90th": [
                95.90147925204919,
                98.38073038073037
            ],
            "95th": [
                95.68961091836012,
                98.582995951417
            ],
            "99th": [
                95.11698035037878,
                98.98585213063207
            ],
            "mean": 97.2024868833469,
            "median": 97.22772277227722
        },
        "recall": {
            "90th": [
                0.943156862745098,
                0.9724977849686043
            ],
            "95th": [
                0.939962379437459,
                0.9751912339915463
            ],
            "99th": [
                0.9339998113207548,
                0.978304173787021
            ],
            "mean": 0.9582241163506731,
            "median": 0.958498023715415
        },
        "support": {
            "90th": [
                479.0,
                531.0
            ],
            "95th": [
                474.0,
                537.0
            ],
            "99th": [
                465.995,
                548.0049999999999
            ],
            "mean": 505.6455,
            "median": 506.0
        },
        "user_accuracy": {
            "90th": [
                94.3156862745098,
                97.24977849686043
            ],
            "95th": [
                93.9962379437459,
                97.51912339915462
            ],
            "99th": [
                93.39998113207548,
                97.8304173787021
            ],
            "mean": 95.8224116350673,
            "median": 95.8498023715415
        }
    },
    "accuracy": {
        "90th": [
            0.955,
            0.974
        ],
        "95th": [
            0.953,
            0.976
        ],
        "99th": [
            0.949,
            0.979
        ],
        "mean": 0.9649325,
        "median": 0.965
    },
    "cohen_kappa": {
        "90th": [
            0.9099837250180672,
            0.9480033797793266
        ],
        "95th": [
            0.9059987778924428,
            0.952
        ],
        "99th": [
            0.8979890290799112,
            0.9579969757822563
        ],
        "mean": 0.929799696641035,
        "median": 0.9299647022099138
    },
    "macro avg": {
        "f1-score": {
            "90th": [
                0.9549837491334372,
                0.9739998959995839
            ],
            "95th": [
                0.9529919145928054,
                0.9759976381651989
            ],
            "99th": [
                0.94897252795839,
                0.9789974586925019
            ],
            "mean": 0.9648966651527466,
            "median": 0.964981475200381
        },
        "precision": {
            "90th": [
                0.955104941734568,
                0.9743239999828023
            ],
            "95th": [
                0.953001291530649,
                0.9760326045572422
            ],
            "99th": [
                0.9490657969053331,
                0.979059976776916
            ],
            "mean": 0.9649528284740974,
            "median": 0.96500093000372
        },
        "recall": {
            "90th": [
                0.9550886141667957,
                0.9744218173408374
            ],
            "95th": [
                0.9532022061331551,
                0.9760925748228884
            ],
            "99th": [
                0.9489679335684154,
                0.979087938758949
            ],
            "mean": 0.9650082715070117,
            "median": 0.9650206501992427
        }
    },
    "weighted avg": {
        "f1-score": {
            "90th": [
                0.9550004455004455,
                0.9740099204063166
            ],
            "95th": [
                0.9530028586407283,
                0.9760007920135364
            ],
            "99th": [
                0.9489970385122285,
                0.9790001932004402
            ],
            "mean": 0.9649335800679643,
            "median": 0.9649998949998949
        },
        "precision": {
            "90th": [
                0.9552299563805391,
                0.9742918173156384
            ],
            "95th": [
                0.9532940937767352,
                0.9760622241505864
            ],
            "99th": [
                0.9490416760198391,
                0.9790980058879342
            ],
            "mean": 0.9651020391425708,
            "median": 0.9650989807996928
        },
        "recall": {
            "90th": [
                0.955,
                0.974
            ],
            "95th": [
                0.953,
                0.976
            ],
            "99th": [
                0.949,
                0.979
            ],
            "mean": 0.9649325,
            "median": 0.965
        }
    }
}