{
    "Mangrove": {
        "f1-score": {
            "90th": [
                0.9628143586201604,
                0.9796708615682479
            ],
            "95th": [
                0.9599178276231177,
                0.9810954660658969
            ],
            "99th": [
                0.9559104530687994,
                0.9848342326337374
            ],
            "mean": 0.9715280588168136,
            "median": 0.9718045112781954
        },
        "precision": {
            "90th": [
                0.9748933742301499,
                0.9921267577309222
            ],
            "95th": [
                0.9727454117473978,
                0.9939519171480495
            ],
            "99th": [
                0.9695817104867382,
                0.996078469744062
            ],
            "mean": 0.984152899683207,
            "median": 0.9841269841269841
        },
        "producer_accuracy": {
            "90th": [
                97.48933742301497,
                99.21267577309222
            ],
            "95th": [
                97.27454117473978,
                99.39519171480495
            ],
            "99th": [
                96.95817104867383,
                99.6078469744062
            ],
            "mean": 98.4152899683207,
            "median": 98.4126984126984
        },
        "recall": {
            "90th": [
                0.9441117764471058,
                0.972870841017798
            ],
            "95th": [
                0.9401544401544402,
                0.9750981617969641
            ],
            "99th": [
                0.9334624892829269,
                0.9806207151498857
            ],
            "mean": 0.9592753620187685,
            "median": 0.9597806215722121
        },
        "support": {
            "90th": [
                487.0,
                540.0
            ],
            "95th": [
                483.0,
                543.0
            ],
            "99th": [
                471.995,
                552.0
            ],
            "mean": 513.352,
            "median": 513.0
        },
        "user_accuracy": {
            "90th": [
                94.41117764471058,
                97.28708410177978
            ],
            "95th": [
                94.01544401544402,
                97.5098161796964
            ],
            "99th": [
                93.3462489282927,
                98.06207151498857
            ],
            "mean": 95.92753620187685,
            "median": 95.97806215722122
        }
    },
    "Other": {
        "f1-score": {
            "90th": [
                0.9613798837831637,
                0.9791439070305883
            ],
            "95th": [
                0.9595939148570727,
                0.9808524002993692
            ],
            "99th": [
                0.9553455285217257,
                0.9838566909948052
            ],
            "mean": 0.9707332496874228,
            "median": 0.971021731891297
        },
        "precision": {
            "90th": [
                0.9429047308503615,
                0.9714892737201313
            ],
            "95th": [
                0.9392109038737446,
                0.974308300395257
            ],
            "99th": [
                0.9316754962854706,
                0.9801589266069464
            ],
            "mean": 0.9581644029153642,
            "median": 0.9587009442885275
        },
        "producer_accuracy": {
            "90th": [
                94.29047308503615,
                97.14892737201312
            ],
            "95th": [
                93.92109038737446,
                97.4308300395257
            ],
            "99th": [
                93.16754962854708,
                98.01589266069463
            ],
            "mean": 95.81644029153642,
            "median": 95.87009442885275
        },
        "recall": {
            "90th": [
                0.9740506000985043,
                0.9919678714859438
            ],
            "95th": [
                0.9719827586206896,
                0.993776255766604
            ],
            "99th": [
                0.9678058635212082,
                0.9957447710061306
            ],
            "mean": 0.983694254218899,
            "median": 0.983739837398374
        },
        "support": {
            "90th": [
                460.0,
                513.0
            ],
            "95th": [
                457.0,
                517.0
            ],
            "99th": [
                448.0,
                528.0049999999999
            ],
            "mean": 486.648,
            "median": 487.0
        },
        "user_accuracy": {
            "90th": [
                97.40506000985043,
                99.19678714859438
            ],
            "95th": [
                97.19827586206897,
                99.3776255766604
            ],
            "99th": [
                96.78058635212082,
                99.57447710061307
            ],
            "mean": 98.3694254218899,
            "median": 98.3739837398374
        }
    },
    "accuracy": {
        "90th": [
            0.962,
            0.979
        ],
        "95th": [
            0.96,
            0.981
        ],
        "99th": [
            0.9559949999999999,
            0.984
        ],
        "mean": 0.9711645,
        "median": 0.971
    },
    "cohen_kappa": {
        "90th": [
            0.924003176660227,
            0.9580033933253087
        ],
        "95th": [
            0.920014357422063,
            0.9619764101456264
        ],
        "99th": [
            0.9119670123756748,
            0.9679755261655467
        ],
        "mean": 0.9422734457360934,
        "median": 0.9420115976804639
    },
    "macro avg": {
        "f1-score": {
            "90th": [
                0.9619876840096192,
                0.9789994917874459
            ],
            "95th": [
                0.9599942391704406,
                0.9809881632261516
            ],
            "99th": [
                0.955965195315785,
                0.9839875076469783
            ],
            "mean": 0.9711306542521181,
            "median": 0.970999738997651
        },
        "precision": {
            "90th": [
                0.9621862014796797,
                0.9792571498421424
            ],
            "95th": [
                0.9601349773464332,
                0.9810055124090851
            ],
            "99th": [
                0.9561765356330073,
                0.9839980141062725
            ],
            "mean": 0.9711586512992856,
            "median": 0.9713412009033366
        },
        "recall": {
            "90th": [
                0.9626857064652211,
                0.9794609550254649
            ],
            "95th": [
                0.9603891011847381,
                0.9810119540337155
            ],
            "99th": [
                0.9561182793770184,
                0.9847330212935481
            ],
            "mean": 0.9714848081188339,
            "median": 0.9717484316203331
        }
    },
    "weighted avg": {
        "f1-score": {
            "90th": [
                0.9620149106781087,
                0.9790079786167892
            ],
            "95th": [
                0.9600063846448014,
                0.9809995342103065
            ],
            "99th": [
                0.9559614808689334,
                0.9840119131977731
            ],
            "mean": 0.9711697159049867,
            "median": 0.971024990935927
        },
        "precision": {
            "90th": [
                0.9627911091118267,
                0.9793538369107637
            ],
            "95th": [
                0.9609766063102311,
                0.9811558122371086
            ],
            "99th": [
                0.9566140326445407,
                0.984302261189543
            ],
            "mean": 0.9715560322767378,
            "median": 0.9717557434677067
        },
        "recall": {
            "90th": [
                0.962,
                0.979
            ],
            "95th": [
                0.96,
                0.981
            ],
            "99th": [
                0.9559949999999999,
                0.984
            ],
            "mean": 0.9711645,
            "median": 0.971
        }
    }
}